dorfwash/__main__.py
dorfwash/config.py
dorfwash/templates/index.html
dorfwash-0.3.0.dist-info/LICENSE
dorfwash-0.3.0.dist-info/METADATA
dorfwash-0.3.0.dist-info/WHEEL
dorfwash-0.3.0.dist-info/RECORD
