Metadata-Version: 2.1
Name: dorfwash
Version: 0.3.0
Summary: A simple webserver, that lets you monitor your Miele washing machines.
Home-page: https://codeberg.org/johann-cm/dorfwash
License: LGPL-3.0-only
Author: Johann Carl Meyer
Author-email: info@johannc.de
Requires-Python: >=3.10,<4.0
Classifier: License :: OSI Approved :: GNU Lesser General Public License v3 (LGPLv3)
Classifier: Programming Language :: Python :: 3
Classifier: Programming Language :: Python :: 3.10
Classifier: Programming Language :: Python :: 3.11
Classifier: Programming Language :: Python :: 3.12
Requires-Dist: flask (>=3.0.3,<4.0.0)
Requires-Dist: flask-caching (>=2.3.0,<3.0.0)
Requires-Dist: pydantic (>=2.7.1,<3.0.0)
Requires-Dist: waitress (>=3.0.0,<4.0.0)
Requires-Dist: washpy (>=0.6.0,<0.7.0)
Project-URL: Repository, https://codeberg.org/johann-cm/dorfwash
